dclean/__init__.py
dclean/cleaning.py
dclean/labeling.py
dclean/preprocessing.py
dclean/privacy.py
tests/__init__.py
tests/test_dclean.py
dataCare-0.1.0.dist-info/LICENSE
dataCare-0.1.0.dist-info/METADATA
dataCare-0.1.0.dist-info/WHEEL
dataCare-0.1.0.dist-info/top_level.txt
dataCare-0.1.0.dist-info/RECORD
