Metadata-Version: 2.1
Name: dataCare
Version: 0.1.0
Summary: A library for automated data cleaning, preprocessing, labeling, and privacy.
Author: Keshav
Author-email: keshgarg24@gmail.com
License-File: LICENSE
Requires-Dist: pandas
Requires-Dist: scikit-learn
Requires-Dist: cryptography
Requires-Dist: pytest
